baygon/__init__.py
baygon/__main__.py
baygon/error.py
baygon/eval.py
baygon/executable.py
baygon/filters.py
baygon/helpers.py
baygon/id.py
baygon/matchers.py
baygon/schema.py
baygon/score.py
baygon/suite.py
baygon-0.6.2.dist-info/METADATA
baygon-0.6.2.dist-info/WHEEL
baygon-0.6.2.dist-info/entry_points.txt
baygon-0.6.2.dist-info/licenses/AUTHORS
baygon-0.6.2.dist-info/licenses/LICENSE.txt
baygon-0.6.2.dist-info/RECORD
