Metadata-Version: 2.4
Name: baygon
Version: 0.6.2
Summary: Functional tests for teaching activities
License: MIT
License-File: AUTHORS
License-File: LICENSE.txt
Keywords: testing,functional-testing
Author: Yves Chevallier
Author-email: yves.chevallier@heig-vd.ch
Requires-Python: >=3.9,<4.0
Classifier: Development Status :: 4 - Beta
Classifier: Environment :: Console
Classifier: Intended Audience :: Developers
Classifier: Intended Audience :: Education
Classifier: Intended Audience :: Science/Research
Classifier: License :: OSI Approved :: MIT License
Classifier: Natural Language :: English
Classifier: Operating System :: MacOS :: MacOS X
Classifier: Operating System :: Microsoft :: Windows
Classifier: Operating System :: OS Independent
Classifier: Operating System :: POSIX
Classifier: Programming Language :: Python
Classifier: Programming Language :: Python :: 3
Classifier: Programming Language :: Python :: 3.9
Classifier: Programming Language :: Python :: 3.10
Classifier: Programming Language :: Python :: 3.11
Classifier: Programming Language :: Python :: 3.12
Classifier: Programming Language :: Python :: 3.13
Classifier: Programming Language :: Python :: 3.14
Classifier: Programming Language :: Python :: 3 :: Only
Classifier: Programming Language :: Python :: 3.8
Classifier: Topic :: Education
Classifier: Topic :: Education :: Testing
Classifier: Topic :: Scientific/Engineering
Classifier: Topic :: Software Development :: Libraries
Classifier: Topic :: Software Development :: Testing
Provides-Extra: test
Requires-Dist: PyYAML (>=6.0,<7.0)
Requires-Dist: click (>=8.1,<9.0)
Requires-Dist: rich (>=13.9.2,<14.0.0)
Requires-Dist: tinykernel (>=0.0.2,<0.0.3)
Requires-Dist: voluptuous (>=0.15,<0.16)
Project-URL: Documentation, https://heig-tin-info.github.io/baygon/
Project-URL: Homepage, https://github.com/heig-tin-info/baygon
Project-URL: Source, https://github.com/heig-tin-info/baygon
Project-URL: Tracker, https://github.com/heig-tin-info/baygon/issues
